h5max/__init__.py
h5max/h5max.py
h5max-0.3.4.dist-info/METADATA
h5max-0.3.4.dist-info/WHEEL
h5max-0.3.4.dist-info/top_level.txt
h5max-0.3.4.dist-info/RECORD
