Metadata-Version: 2.4
Name: h5max
Version: 0.3.4
Summary: scipy.sparse support on h5py
Home-page: https://github.com/jdcla/h5max
Author: Jim Clauwaert
Requires-Python: >=3.9
Requires-Dist: numpy>=1.21.0
Requires-Dist: scipy>=1.7.3
Requires-Dist: h5py>=3.15.1
